ggun/__init__.py
ggun/main.py
ggun/commands/__init__.py
ggun/commands/test.py
utils/__init__.py
utils/api_call.py
utils/list_files.py
ggun-0.1.5.dist-info/METADATA
ggun-0.1.5.dist-info/WHEEL
ggun-0.1.5.dist-info/entry_points.txt
ggun-0.1.5.dist-info/top_level.txt
ggun-0.1.5.dist-info/RECORD
