Metadata-Version: 2.1
Name: ggun
Version: 0.1.5
Summary: Ggun (Gatling Gun) CLI tool for smart contract management and development.
Author: GatlingX
Author-email: hello@gatlingx.com
Requires-Dist: argparse
Requires-Dist: requests
